MANIFEST.in
README.md
setup.py
pslgraph/__init__.py
pslgraph/baseline_mean.py
pslgraph/collaborative_filtering.py
pslgraph/collaborative_filtering_link_prediction.py
pslgraph/config.py
pslgraph/constants.py
pslgraph/graph_matching.py
pslgraph/graph_matching_link_prediction.py
pslgraph/graph_transform.py
pslgraph/link_prediction.py
pslgraph/networkx.py
pslgraph/psl.py
pslgraph/util.py
pslgraph.egg-info/PKG-INFO
pslgraph.egg-info/SOURCES.txt
pslgraph.egg-info/dependency_links.txt
pslgraph.egg-info/entry_points.txt
pslgraph.egg-info/requires.txt
pslgraph.egg-info/top_level.txt
pslgraph/psl-cli/__init__.py
pslgraph/psl-cli/link_prediction.psl
pslgraph/psl-cli/link_prediction_template.data
pslgraph/psl-cli/psl-cli-CANARY-2.1.1.jar