Metadata-Version: 1.2
Name: pslgraph
Version: 0.3.1
Summary: Graph and PSL based TA1 primitive for D3M
Home-page: https://gitlab.datadrivendiscovery.org/dhartnett/psl
Maintainer: Eriq Augustine
Maintainer-email: eaugusti@ucsc.edu
License: UNKNOWN
Keywords: d3m_primitive
Platform: UNKNOWN
Classifier: Programming Language :: Python :: 3.6
Requires-Python: >=3.6
